milspend_2.py
milspend_2-0.0.1.dist-info/METADATA
milspend_2-0.0.1.dist-info/WHEEL
milspend_2-0.0.1.dist-info/entry_points.txt
milspend_2-0.0.1.dist-info/top_level.txt
milspend_2-0.0.1.dist-info/RECORD
