Metadata-Version: 2.1
Name: milspend-2
Version: 0.0.1
Summary: Manufacturing Hourly Earnings 2017
Home-page: https://github.com/NichihoYamauchi/milspend_2.py
Author: nichiho yamauchi
Author-email: s2022032@stu.musashino-u.ac.jp
License: UNKNOWN
Project-URL: Bug Tracker, https://github.com/NichihoYamauchi/milspend_2.py
Platform: UNKNOWN
Classifier: Programming Language :: Python :: 3
Classifier: License :: OSI Approved :: MIT License
Classifier: Operating System :: OS Independent
Requires-Python: >=3.7
